AllenZhouTest123/__init__.py
AllenZhouTest123-0.1.dist-info/LICENSE.txt
AllenZhouTest123-0.1.dist-info/METADATA
AllenZhouTest123-0.1.dist-info/WHEEL
AllenZhouTest123-0.1.dist-info/top_level.txt
AllenZhouTest123-0.1.dist-info/RECORD
