Metadata-Version: 2.1
Name: AllenZhouTest123
Version: 0.1
Summary: Test
Home-page: https://github.com/
Download-URL: https://github.com/
Author: Zhou
Author-email: 13566781276@163.com
License: MIT
Keywords: Test
Classifier: Development Status :: 3 - Alpha
Classifier: Intended Audience :: Developers
Classifier: Topic :: Software Development :: Build Tools
Classifier: License :: OSI Approved :: MIT License
Classifier: Programming Language :: Python :: 3.7
Classifier: Programming Language :: Python :: 3.8
Classifier: Programming Language :: Python :: 3.9
License-File: LICENSE.txt
Requires-Dist: opencv-python
Requires-Dist: mediapipe==0.8.7
